{
  "郑如放": {
    "last_known_pushed_at": "2026-01-30T12:43:08Z",
    "last_viewed_at": "2026-02-04T06:25:46.154312+00:00",
    "commits_count": 10
  },
  "杜银珊": {
    "last_known_pushed_at": "2026-02-03T13:07:22Z",
    "last_viewed_at": "2026-02-04T05:56:30.655812+00:00",
    "commits_count": 6
  },
  "李灿峰": {
    "last_known_pushed_at": "2026-02-03T14:30:56Z",
    "last_viewed_at": "2026-02-04T05:57:16.955677+00:00",
    "commits_count": 2
  },
  "潘俊泽": {
    "last_known_pushed_at": "2026-02-03T08:35:44Z",
    "last_viewed_at": "2026-02-04T06:26:13.590779+00:00",
    "commits_count": 3
  },
  "余昊然": {
    "last_known_pushed_at": "2026-02-03T13:24:47Z",
    "last_viewed_at": "2026-02-04T06:26:02.883778+00:00",
    "commits_count": 1
  },
  "王梓茵": {
    "last_known_pushed_at": "2026-02-02T16:07:06Z",
    "last_viewed_at": "2026-02-04T06:26:08.677001+00:00"
  },
  "李世涵": {
    "last_known_pushed_at": "2026-02-03T15:46:33Z",
    "last_viewed_at": "2026-02-04T05:58:06.562963+00:00",
    "commits_count": 7
  },
  "卿子懿": {
    "last_known_pushed_at": "2026-02-03T15:41:39Z",
    "last_viewed_at": "2026-02-04T05:58:27.936812+00:00",
    "commits_count": 4
  },
  "汤文博": {
    "last_known_pushed_at": "2026-02-03T04:31:11Z",
    "last_viewed_at": "2026-02-04T05:58:38.866541+00:00",
    "commits_count": 5
  },
  "张丹": {
    "last_known_pushed_at": "2026-02-02T08:06:39Z",
    "last_viewed_at": "2026-02-04T05:58:46.519531+00:00",
    "commits_count": 2
  },
  "庄坤达": {
    "last_known_pushed_at": "2026-02-03T14:06:01Z",
    "last_viewed_at": "2026-02-04T05:58:52.590863+00:00",
    "commits_count": 1
  },
  "邓婕婧": {
    "last_known_pushed_at": "2026-02-03T15:48:11Z",
    "last_viewed_at": "2026-02-04T05:59:11.105721+00:00",
    "commits_count": 6
  },
  "蔡家豪": {
    "last_known_pushed_at": "2025-11-11T12:42:14Z",
    "last_viewed_at": "2026-02-04T05:59:25.298980+00:00",
    "commits_count": 1
  },
  "冯润松": {
    "last_known_pushed_at": "2026-02-03T09:32:25Z",
    "last_viewed_at": "2026-02-04T05:59:29.820984+00:00",
    "commits_count": 1
  },
  "赖昌健": {
    "last_known_pushed_at": "2026-02-03T12:00:57Z",
    "last_viewed_at": "2026-02-04T05:59:35.517388+00:00",
    "commits_count": 3
  },
  "刘冠德": {
    "last_known_pushed_at": "2026-02-03T15:57:29Z",
    "last_viewed_at": "2026-02-04T05:59:50.336370+00:00",
    "commits_count": 1
  },
  "罗振坚": {
    "last_known_pushed_at": "2026-02-03T15:04:13Z",
    "last_viewed_at": "2026-02-04T05:59:56.491122+00:00",
    "commits_count": 2
  },
  "丘一君": {
    "last_known_pushed_at": "2026-02-02T07:59:51Z",
    "last_viewed_at": "2026-02-04T06:00:03.140708+00:00",
    "commits_count": 1
  },
  "叶思怿": {
    "last_known_pushed_at": "2026-02-04T05:01:42Z",
    "last_viewed_at": "2026-02-04T06:23:23.325004+00:00",
    "commits_count": 7
  },
  "张致远": {
    "last_known_pushed_at": "2026-02-03T12:32:42Z",
    "last_viewed_at": "2026-02-04T06:00:33.344600+00:00",
    "commits_count": 6
  },
  "周梓澳": {
    "last_known_pushed_at": "2026-02-04T03:55:19Z",
    "last_viewed_at": "2026-02-04T06:56:32.815623+00:00",
    "commits_count": 16
  },
  "袁睿": {
    "last_known_pushed_at": "2026-02-04T07:01:09Z",
    "last_viewed_at": "2026-02-04T08:18:42.287007+00:00",
    "commits_count": 6
  },
  "陈泳锦": {
    "last_known_pushed_at": "2026-02-02T15:19:57Z",
    "last_viewed_at": "2026-02-04T06:00:43.131443+00:00"
  },
  "龚洙琳": {
    "last_known_pushed_at": "2026-02-02T09:31:49Z",
    "last_viewed_at": "2026-02-04T06:00:44.598790+00:00"
  },
  "廖柏翔": {
    "last_known_pushed_at": "2026-02-02T17:04:25Z",
    "last_viewed_at": "2026-02-04T06:00:45.753970+00:00",
    "commits_count": 4
  },
  "沈沛霖": {
    "last_known_pushed_at": "2026-02-03T15:13:51Z",
    "last_viewed_at": "2026-02-04T08:21:39.110219+00:00",
    "commits_count": 7
  },
  "谢采如": {
    "last_known_pushed_at": "2026-02-02T08:56:19Z",
    "last_viewed_at": "2026-02-04T08:21:33.200553+00:00"
  },
  "叶鑫浩": {
    "last_known_pushed_at": "2026-02-03T06:09:05Z",
    "last_viewed_at": "2026-02-04T08:21:21.604881+00:00",
    "commits_count": 5
  },
  "姚晨": {
    "last_known_pushed_at": "2026-02-02T12:20:35Z",
    "last_viewed_at": "2026-02-04T06:00:52.666061+00:00"
  },
  "赵崇杰": {
    "last_known_pushed_at": "2026-02-03T15:10:16Z",
    "last_viewed_at": "2026-02-04T06:00:55.187126+00:00"
  },
  "范俊明": {
    "last_known_pushed_at": "2026-02-03T15:06:19Z",
    "last_viewed_at": "2026-02-04T06:00:57.841321+00:00"
  },
  "黄熙晨": {
    "last_known_pushed_at": "2026-02-04T02:48:28Z",
    "last_viewed_at": "2026-02-04T06:23:53.841766+00:00"
  },
  "李俊杰": {
    "last_known_pushed_at": "2026-02-03T09:15:35Z",
    "last_viewed_at": "2026-02-04T06:01:02.742093+00:00"
  },
  "林观鑫": {
    "last_known_pushed_at": "2026-02-02T07:58:55Z",
    "last_viewed_at": "2026-02-04T06:01:04.881837+00:00"
  },
  "苏芷兰": {
    "last_known_pushed_at": "2026-02-02T12:26:04Z",
    "last_viewed_at": "2026-02-04T06:56:23.624307+00:00"
  },
  "杨与齐": {
    "last_known_pushed_at": "2026-02-03T12:18:19Z",
    "last_viewed_at": "2026-02-04T06:01:08.682135+00:00"
  },
  "郑壕煜": {
    "last_known_pushed_at": "2026-02-03T12:54:52Z",
    "last_viewed_at": "2026-02-04T06:24:15.464198+00:00"
  },
  "邹家仪": {
    "last_known_pushed_at": "2026-02-02T09:25:32Z",
    "last_viewed_at": "2026-02-04T06:01:12.282401+00:00"
  },
  "陈绮旋": {
    "last_known_pushed_at": "2026-02-02T21:27:20Z",
    "last_viewed_at": "2026-02-04T06:24:05.130444+00:00"
  }
}